nyflow/__init__.py
nyflow/core.py
nyflow/core_simple.py
nyflow/functions.py
nyflow/utils.py
nyflow-0.0.7.6.dist-info/METADATA
nyflow-0.0.7.6.dist-info/RECORD
nyflow-0.0.7.6.dist-info/WHEEL
nyflow-0.0.7.6.dist-info/top_level.txt
